README.md
setup.py
bibi/__init__.py
bibi/bibi.py
bibi.egg-info/PKG-INFO
bibi.egg-info/SOURCES.txt
bibi.egg-info/dependency_links.txt
bibi.egg-info/entry_points.txt
bibi.egg-info/not-zip-safe
bibi.egg-info/requires.txt
bibi.egg-info/top_level.txt