Metadata-Version: 1.0
Name: bibi
Version: 0.2.3
Summary: Simple way to publish your blog
Home-page: https://github.com/ipconfiger/bibi
Author: Alexander.Li
Author-email: superpowerlee@gmail.com
License: MIT
Platform: UNKNOWN
